bytedmathics3/__init__.py
bytedmathics3-0.0.1.dist-info/METADATA
bytedmathics3-0.0.1.dist-info/WHEEL
bytedmathics3-0.0.1.dist-info/top_level.txt
bytedmathics3-0.0.1.dist-info/RECORD
