Metadata-Version: 2.1
Name: bytedmathics3
Version: 0.0.1
Summary: A simple package named bytedmathics3
Home-page: https://github.com/artifact/bytedmathics3.git
Author: artifact
Author-email: artifact@example.com
License: UNKNOWN
Platform: UNKNOWN
Classifier: Programming Language :: Python :: 3
Classifier: License :: OSI Approved :: MIT License
Classifier: Operating System :: OS Independent
